kekagui/__init__.py
kekagui/api.py
kekagui/middleware.py
kekagui/response.py
kekagui-0.0.4.dist-info/METADATA
kekagui-0.0.4.dist-info/WHEEL
kekagui-0.0.4.dist-info/top_level.txt
kekagui-0.0.4.dist-info/RECORD
