Metadata-Version: 2.1
Name: kekagui
Version: 0.0.4
Summary: Bumbo Python Web Framework built for learning purposes.
Home-page: UNKNOWN
Author: Jahongir Rahmonov
Author-email: jrahmonov2@gmail.com
License: MIT
Platform: UNKNOWN
Classifier: Programming Language :: Python :: 3.6
Requires-Python: >=3.6.0
Requires-Dist: Jinja2 (==2.10.3)
Requires-Dist: parse (==1.12.1)
Requires-Dist: requests (==2.22.0)
Requires-Dist: requests-wsgi-adapter (==0.4.1)
Requires-Dist: WebOb (==1.8.5)
Requires-Dist: whitenoise (==4.1.4)
